trclab/__init__.py
trclab/ich_image.py
trclab/application/__init__.py
trclab/application/trclab.py
trclab/application/datasets/__init__.py
trclab/application/datasets/dataset.py
trclab/application/datasets/dataset_file_manager.py
trclab/application/datasets/dataset_manager.py
trclab/application/datasets/dataset_type.py
trclab/application/exception/__init__.py
trclab/datasets/__init__.py
trclab/datasets/ich_127.py
trclab/datasets/ich_2500.py
trclab/datasets/ich_420.py
trclab/datasets/rsna_ich.py
trclab/ich/__init__.py
trclab/ich/ich_type.py
trclab/img/__init__.py
trclab/img/image_type.py
trclab-0.1.0.dist-info/LICENSE
trclab-0.1.0.dist-info/METADATA
trclab-0.1.0.dist-info/WHEEL
trclab-0.1.0.dist-info/top_level.txt
trclab-0.1.0.dist-info/RECORD
